README.rst
setup.py
collectd_cdn/__init__.py
collectd_cdn/fastly.py
collectd_cdn.egg-info/PKG-INFO
collectd_cdn.egg-info/SOURCES.txt
collectd_cdn.egg-info/dependency_links.txt
collectd_cdn.egg-info/requires.txt
collectd_cdn.egg-info/top_level.txt