Metadata-Version: 1.0
Name: collectd-cdn
Version: 0.2.1
Summary: CDN stats plugin for collectd
Home-page: https://github.com/gds-operations/collectd-cdn
Author: Government Digital Service
Author-email: dan.carley@gmail.com
License: MIT
Keywords: collectd cdn stats fastly
Platform: UNKNOWN
